README.rst
setup.py
pyethmobisir/__init__.py
pyethmobisir/client.py
pyethmobisir/constants.py
pyethmobisir/exceptions.py
pyethmobisir/utils.py
pyethmobisir.egg-info/PKG-INFO
pyethmobisir.egg-info/SOURCES.txt
pyethmobisir.egg-info/dependency_links.txt
pyethmobisir.egg-info/requires.txt
pyethmobisir.egg-info/top_level.txt