Metadata-Version: 1.1
Name: pyethmobisir
Version: 0.1
Summary: ethereum JSON-RPC client
Home-page: https://github.com/balakrishnan2/pyethmobisir
Author: balakrishnan
Author-email: krishnasmartt@gmail.com
License: Unlicense
Platform: UNKNOWN
Classifier: Development Status :: 4 - Beta
Classifier: Intended Audience :: Developers
Classifier: License :: Public Domain
Classifier: Operating System :: OS Independent
Classifier: Programming Language :: Python
Classifier: Programming Language :: Python :: 2
